mrvaldez.py
setup.py
mrvaldez.egg-info/PKG-INFO
mrvaldez.egg-info/SOURCES.txt
mrvaldez.egg-info/dependency_links.txt
mrvaldez.egg-info/top_level.txt