Metadata-Version: 1.0
Name: mrvaldez
Version: 0.1.1
Summary: Mr. Valdez has no first name
Home-page: UNKNOWN
Author: Mark Steve Samson
Author-email: contact@marksteve.me
License: UNKNOWN
Platform: UNKNOWN
